certbot_dns_powerdns/__init__.py
certbot_dns_powerdns/dns_powerdns.py
certbot_dns_powerdns/dns_powerdns_test.py
certbot_dns_powerdns_admin-0.2.3.dist-info/METADATA
certbot_dns_powerdns_admin-0.2.3.dist-info/WHEEL
certbot_dns_powerdns_admin-0.2.3.dist-info/entry_points.txt
certbot_dns_powerdns_admin-0.2.3.dist-info/top_level.txt
certbot_dns_powerdns_admin-0.2.3.dist-info/RECORD
