Metadata-Version: 2.1
Name: certbot-dns-powerdns-admin
Version: 0.2.3
Summary: PowerDNS DNS Authenticator plugin for Certbot
Home-page: https://github.com/pan-net-security/certbot-dns-powerdns
Author: DT Pan-Net s.r.o
Author-email: pannet.security@pan-net.eu
License: Apache License 2.0
Classifier: Development Status :: 5 - Production/Stable
Classifier: Environment :: Plugins
Classifier: Intended Audience :: System Administrators
Classifier: License :: OSI Approved :: Apache Software License
Classifier: Operating System :: POSIX :: Linux
Classifier: Programming Language :: Python
Classifier: Programming Language :: Python :: 2
Classifier: Programming Language :: Python :: 2.7
Classifier: Programming Language :: Python :: 3
Classifier: Programming Language :: Python :: 3.5
Classifier: Programming Language :: Python :: 3.6
Classifier: Programming Language :: Python :: 3.7
Classifier: Topic :: Internet :: WWW/HTTP
Classifier: Topic :: Security
Classifier: Topic :: System :: Installation/Setup
Classifier: Topic :: System :: Networking
Classifier: Topic :: System :: Systems Administration
Classifier: Topic :: Utilities
Requires-Python: >=2.7, !=3.0.*, !=3.1.*, !=3.2.*, !=3.3.*
Requires-Dist: acme
Requires-Dist: certbot
Requires-Dist: dns-lexicon
Requires-Dist: dnspython
Requires-Dist: mock
Requires-Dist: setuptools
Requires-Dist: zope.interface
Requires-Dist: requests
